{
  "firstLayout": "",
  "gdVersion": {
    "build": 99,
    "major": 4,
    "minor": 0,
    "revision": 0
  },
  "properties": {
    "adaptGameResolutionAtRuntime": true,
    "folderProject": false,
    "orientation": "portrait",
    "packageName": "com.wichigame.dinopong",
    "pixelsRounding": true,
    "projectUuid": "b12f41e9-3c9e-40af-a3db-e85b96bf3b42",
    "scaleMode": "nearest",
    "sizeOnStartupMode": "adaptWidth",
    "templateSlug": "",
    "useExternalSourceFiles": false,
    "version": "1.0.0",
    "name": "DinoPong",
    "description": "",
    "author": "Wilfredo_Chipana",
    "windowWidth": 600,
    "windowHeight": 600,
    "latestCompilationDirectory": "",
    "maxFPS": 60,
    "minFPS": 40,
    "verticalSync": false,
    "platformSpecificAssets": {},
    "loadingScreen": {
      "backgroundColor": 0,
      "backgroundFadeInDuration": 0.2,
      "backgroundImageResourceName": "",
      "gdevelopLogoStyle": "light",
      "logoAndProgressFadeInDuration": 0.2,
      "logoAndProgressLogoFadeInDelay": 0.2,
      "minDuration": 1.5,
      "progressBarColor": 16777215,
      "progressBarHeight": 20,
      "progressBarMaxWidth": 200,
      "progressBarMinWidth": 40,
      "progressBarWidthPercent": 30,
      "showGDevelopSplash": true,
      "showProgressBar": true
    },
    "authorIds": [
      "w0RBjpwkO5WizYBxTKh40y1cwsC3"
    ],
    "categories": [],
    "playableDevices": [],
    "extensionProperties": [
      {
        "extension": "AdMob",
        "property": "AdMobAppId",
        "value": ""
      }
    ],
    "platforms": [
      {
        "name": "GDevelop JS platform"
      }
    ],
    "currentPlatform": "GDevelop JS platform"
  },
  "resources": {
    "resources": [
      {
        "alwaysLoaded": false,
        "file": "Assets/Terreno0.png",
        "kind": "image",
        "metadata": "",
        "name": "Assets\\Terreno0.png",
        "smoothed": false,
        "userAdded": false
      },
      {
        "alwaysLoaded": false,
        "file": "Assets/spr_rockyStop_0.png",
        "kind": "image",
        "metadata": "",
        "name": "Assets\\spr_rockyStop_0.png",
        "smoothed": false,
        "userAdded": false
      },
      {
        "alwaysLoaded": false,
        "file": "Assets/spr_turtleBall_0.png",
        "kind": "image",
        "metadata": "",
        "name": "Assets\\spr_turtleBall_0.png",
        "smoothed": false,
        "userAdded": false
      },
      {
        "alwaysLoaded": false,
        "file": "Assets/spr_dino_0.png",
        "kind": "image",
        "metadata": "",
        "name": "Assets\\spr_dino_0.png",
        "smoothed": false,
        "userAdded": false
      },
      {
        "alwaysLoaded": false,
        "file": "Assets/spr_dino_1.png",
        "kind": "image",
        "metadata": "",
        "name": "Assets\\spr_dino_1.png",
        "smoothed": false,
        "userAdded": false
      },
      {
        "alwaysLoaded": false,
        "file": "Assets/spr_solido_0.png",
        "kind": "image",
        "metadata": "",
        "name": "Assets\\spr_solido_0.png",
        "smoothed": false,
        "userAdded": true
      }
    ],
    "resourceFolders": []
  },
  "objects": [],
  "objectsGroups": [],
  "variables": [
    {
      "name": "speedBall",
      "type": "string",
      "value": "80"
    },
    {
      "name": "Score",
      "type": "string",
      "value": "0"
    }
  ],
  "layouts": [
    {
      "b": 74,
      "disableInputWhenNotFocused": true,
      "mangledName": "New_32scene",
      "name": "New scene",
      "oglFOV": 90,
      "oglZFar": 500,
      "oglZNear": 1,
      "r": 74,
      "standardSortMethod": true,
      "stopSoundsOnStartup": true,
      "title": "DinoPong",
      "v": 74,
      "uiSettings": {
        "grid": false,
        "gridType": "rectangular",
        "gridWidth": 32,
        "gridHeight": 32,
        "gridOffsetX": 0,
        "gridOffsetY": 0,
        "gridColor": 10401023,
        "gridAlpha": 0.8,
        "snap": true,
        "zoomFactor": 0.8780000000000001,
        "windowMask": false
      },
      "objectsGroups": [],
      "variables": [],
      "instances": [
        {
          "angle": 0,
          "customSize": true,
          "height": 608,
          "layer": "",
          "locked": false,
          "name": "Fondo",
          "persistentUuid": "34f5d385-620e-4ab1-b7e4-7b5f303f0791",
          "width": 605,
          "x": -1,
          "y": -4,
          "zOrder": 1,
          "numberProperties": [],
          "stringProperties": [],
          "initialVariables": []
        },
        {
          "angle": 0,
          "customSize": false,
          "height": 0,
          "layer": "",
          "locked": false,
          "name": "Rocky",
          "persistentUuid": "576095c5-c424-4cb2-871d-274971e3553f",
          "width": 0,
          "x": 300,
          "y": 522,
          "zOrder": 2,
          "numberProperties": [],
          "stringProperties": [],
          "initialVariables": []
        },
        {
          "angle": 0,
          "customSize": false,
          "height": 0,
          "layer": "",
          "locked": false,
          "name": "Ball",
          "persistentUuid": "a9e1d488-a3d5-49dd-9eb8-dfa3c5fb6bcd",
          "width": 0,
          "x": 345,
          "y": 518,
          "zOrder": 3,
          "numberProperties": [],
          "stringProperties": [],
          "initialVariables": []
        },
        {
          "angle": 0,
          "customSize": false,
          "height": 0,
          "layer": "",
          "locked": false,
          "name": "SolidoD",
          "persistentUuid": "1fc96a75-392e-4f09-8a92-3467077156fc",
          "width": 0,
          "x": 506,
          "y": 1,
          "zOrder": 4,
          "numberProperties": [],
          "stringProperties": [],
          "initialVariables": []
        },
        {
          "angle": 0,
          "customSize": false,
          "height": 0,
          "layer": "",
          "locked": false,
          "name": "SolidoI",
          "persistentUuid": "9d19b695-b257-43e3-b999-89a18d760d8f",
          "width": 0,
          "x": 63,
          "y": 3,
          "zOrder": 5,
          "numberProperties": [],
          "stringProperties": [],
          "initialVariables": []
        },
        {
          "angle": 0,
          "customSize": false,
          "height": 0,
          "layer": "",
          "locked": false,
          "name": "Score",
          "persistentUuid": "557fa638-0f6d-4ba3-88a7-1c24379fffd1",
          "width": 0,
          "x": 277,
          "y": 16,
          "zOrder": 6,
          "numberProperties": [],
          "stringProperties": [],
          "initialVariables": []
        },
        {
          "angle": 90,
          "customSize": false,
          "height": 0,
          "layer": "",
          "locked": false,
          "name": "SolidUp",
          "persistentUuid": "72c92fd3-55e9-410c-a90c-559661c5afd1",
          "width": 0,
          "x": 285,
          "y": -287,
          "zOrder": 7,
          "numberProperties": [],
          "stringProperties": [],
          "initialVariables": []
        },
        {
          "angle": 90,
          "customSize": false,
          "height": 0,
          "layer": "",
          "locked": false,
          "name": "SolidDown",
          "persistentUuid": "1f346747-4282-413b-976d-19a31916186f",
          "width": 0,
          "x": 297.4262390136719,
          "y": 277.6788635253906,
          "zOrder": 8,
          "numberProperties": [],
          "stringProperties": [],
          "initialVariables": []
        },
        {
          "angle": 0,
          "customSize": false,
          "height": 0,
          "layer": "",
          "locked": false,
          "name": "debugger",
          "persistentUuid": "d336ea83-e09f-4c3b-8de9-cc4ddac0cf5c",
          "width": 0,
          "x": 118,
          "y": 83,
          "zOrder": 9,
          "numberProperties": [],
          "stringProperties": [],
          "initialVariables": []
        }
      ],
      "objects": [
        {
          "assetStoreId": "",
          "name": "Fondo",
          "tags": "",
          "type": "Sprite",
          "updateIfNotVisible": false,
          "variables": [],
          "effects": [],
          "behaviors": [],
          "animations": [
            {
              "name": "",
              "useMultipleDirections": false,
              "directions": [
                {
                  "looping": false,
                  "timeBetweenFrames": 0.08,
                  "sprites": [
                    {
                      "hasCustomCollisionMask": false,
                      "image": "Assets\\Terreno0.png",
                      "points": [],
                      "originPoint": {
                        "name": "origine",
                        "x": 0,
                        "y": 0
                      },
                      "centerPoint": {
                        "automatic": true,
                        "name": "centre",
                        "x": 0,
                        "y": 0
                      },
                      "customCollisionMask": []
                    }
                  ]
                }
              ]
            }
          ]
        },
        {
          "assetStoreId": "",
          "name": "Rocky",
          "tags": "",
          "type": "Sprite",
          "updateIfNotVisible": false,
          "variables": [],
          "effects": [],
          "behaviors": [],
          "animations": [
            {
              "name": "",
              "useMultipleDirections": false,
              "directions": [
                {
                  "looping": false,
                  "timeBetweenFrames": 0.08,
                  "sprites": [
                    {
                      "hasCustomCollisionMask": false,
                      "image": "Assets\\spr_rockyStop_0.png",
                      "points": [],
                      "originPoint": {
                        "name": "origine",
                        "x": 0,
                        "y": 0
                      },
                      "centerPoint": {
                        "automatic": true,
                        "name": "centre",
                        "x": 0,
                        "y": 0
                      },
                      "customCollisionMask": []
                    }
                  ]
                }
              ]
            }
          ]
        },
        {
          "assetStoreId": "",
          "name": "Ball",
          "tags": "",
          "type": "Sprite",
          "updateIfNotVisible": false,
          "variables": [
            {
              "name": "Speed",
              "type": "string",
              "value": "300"
            },
            {
              "name": "DirX",
              "type": "number",
              "value": 10
            },
            {
              "name": "State",
              "type": "string",
              "value": "stop"
            },
            {
              "name": "DirY",
              "type": "number",
              "value": -10
            }
          ],
          "effects": [],
          "behaviors": [],
          "animations": [
            {
              "name": "",
              "useMultipleDirections": false,
              "directions": [
                {
                  "looping": false,
                  "timeBetweenFrames": 0.08,
                  "sprites": [
                    {
                      "hasCustomCollisionMask": false,
                      "image": "Assets\\spr_turtleBall_0.png",
                      "points": [],
                      "originPoint": {
                        "name": "origine",
                        "x": 0,
                        "y": 0
                      },
                      "centerPoint": {
                        "automatic": true,
                        "name": "centre",
                        "x": 0,
                        "y": 0
                      },
                      "customCollisionMask": []
                    }
                  ]
                }
              ]
            }
          ]
        },
        {
          "assetStoreId": "",
          "name": "Dino",
          "tags": "",
          "type": "Sprite",
          "updateIfNotVisible": false,
          "variables": [],
          "effects": [],
          "behaviors": [],
          "animations": [
            {
              "name": "",
              "useMultipleDirections": false,
              "directions": [
                {
                  "looping": true,
                  "timeBetweenFrames": 0.08,
                  "sprites": [
                    {
                      "hasCustomCollisionMask": false,
                      "image": "Assets\\spr_dino_0.png",
                      "points": [],
                      "originPoint": {
                        "name": "origine",
                        "x": 0,
                        "y": 0
                      },
                      "centerPoint": {
                        "automatic": true,
                        "name": "centre",
                        "x": 0,
                        "y": 0
                      },
                      "customCollisionMask": []
                    },
                    {
                      "hasCustomCollisionMask": false,
                      "image": "Assets\\spr_dino_1.png",
                      "points": [],
                      "originPoint": {
                        "name": "origine",
                        "x": 0,
                        "y": 0
                      },
                      "centerPoint": {
                        "automatic": true,
                        "name": "centre",
                        "x": 0,
                        "y": 0
                      },
                      "customCollisionMask": []
                    },
                    {
                      "hasCustomCollisionMask": false,
                      "image": "Assets\\spr_dino_0.png",
                      "points": [],
                      "originPoint": {
                        "name": "origine",
                        "x": 0,
                        "y": 0
                      },
                      "centerPoint": {
                        "automatic": true,
                        "name": "centre",
                        "x": 0,
                        "y": 0
                      },
                      "customCollisionMask": []
                    },
                    {
                      "hasCustomCollisionMask": false,
                      "image": "Assets\\spr_dino_1.png",
                      "points": [],
                      "originPoint": {
                        "name": "origine",
                        "x": 0,
                        "y": 0
                      },
                      "centerPoint": {
                        "automatic": true,
                        "name": "centre",
                        "x": 0,
                        "y": 0
                      },
                      "customCollisionMask": []
                    }
                  ]
                }
              ]
            }
          ]
        },
        {
          "assetStoreId": "",
          "name": "SolidDown",
          "tags": "",
          "type": "Sprite",
          "updateIfNotVisible": false,
          "variables": [],
          "effects": [],
          "behaviors": [
            {
              "name": "Physics2",
              "type": "Physics2::Physics2Behavior",
              "bodyType": "Static",
              "bullet": false,
              "fixedRotation": false,
              "canSleep": true,
              "shape": "Box",
              "shapeDimensionA": 0,
              "shapeDimensionB": 0,
              "shapeOffsetX": 0,
              "shapeOffsetY": 0,
              "polygonOrigin": "Center",
              "vertices": [],
              "density": 1,
              "friction": 0.3,
              "restitution": 0.1,
              "linearDamping": 0.1,
              "angularDamping": 0.1,
              "gravityScale": 0,
              "layers": 1,
              "masks": 1
            }
          ],
          "animations": [
            {
              "name": "",
              "useMultipleDirections": false,
              "directions": [
                {
                  "looping": false,
                  "timeBetweenFrames": 0.08,
                  "sprites": [
                    {
                      "hasCustomCollisionMask": false,
                      "image": "Assets\\spr_solido_0.png",
                      "points": [],
                      "originPoint": {
                        "name": "origine",
                        "x": 0,
                        "y": 0
                      },
                      "centerPoint": {
                        "automatic": true,
                        "name": "centre",
                        "x": 0,
                        "y": 0
                      },
                      "customCollisionMask": []
                    }
                  ]
                }
              ]
            }
          ]
        },
        {
          "assetStoreId": "",
          "name": "SolidUp",
          "tags": "",
          "type": "Sprite",
          "updateIfNotVisible": false,
          "variables": [],
          "effects": [],
          "behaviors": [],
          "animations": [
            {
              "name": "",
              "useMultipleDirections": false,
              "directions": [
                {
                  "looping": false,
                  "timeBetweenFrames": 0.08,
                  "sprites": [
                    {
                      "hasCustomCollisionMask": false,
                      "image": "Assets\\spr_solido_0.png",
                      "points": [],
                      "originPoint": {
                        "name": "origine",
                        "x": 0,
                        "y": 0
                      },
                      "centerPoint": {
                        "automatic": true,
                        "name": "centre",
                        "x": 0,
                        "y": 0
                      },
                      "customCollisionMask": []
                    }
                  ]
                }
              ]
            }
          ]
        },
        {
          "assetStoreId": "",
          "name": "SolidoD",
          "tags": "",
          "type": "Sprite",
          "updateIfNotVisible": false,
          "variables": [],
          "effects": [],
          "behaviors": [],
          "animations": [
            {
              "name": "",
              "useMultipleDirections": false,
              "directions": [
                {
                  "looping": false,
                  "timeBetweenFrames": 0.08,
                  "sprites": [
                    {
                      "hasCustomCollisionMask": false,
                      "image": "Assets\\spr_solido_0.png",
                      "points": [],
                      "originPoint": {
                        "name": "origine",
                        "x": 0,
                        "y": 0
                      },
                      "centerPoint": {
                        "automatic": true,
                        "name": "centre",
                        "x": 0,
                        "y": 0
                      },
                      "customCollisionMask": []
                    }
                  ]
                }
              ]
            }
          ]
        },
        {
          "assetStoreId": "",
          "name": "SolidoI",
          "tags": "",
          "type": "Sprite",
          "updateIfNotVisible": false,
          "variables": [],
          "effects": [],
          "behaviors": [],
          "animations": [
            {
              "name": "",
              "useMultipleDirections": false,
              "directions": [
                {
                  "looping": false,
                  "timeBetweenFrames": 0.08,
                  "sprites": [
                    {
                      "hasCustomCollisionMask": false,
                      "image": "Assets\\spr_solido_0.png",
                      "points": [],
                      "originPoint": {
                        "name": "origine",
                        "x": 0,
                        "y": 0
                      },
                      "centerPoint": {
                        "automatic": true,
                        "name": "centre",
                        "x": 0,
                        "y": 0
                      },
                      "customCollisionMask": []
                    }
                  ]
                }
              ]
            }
          ]
        },
        {
          "assetStoreId": "",
          "bold": false,
          "italic": false,
          "name": "Score",
          "smoothed": true,
          "tags": "",
          "type": "TextObject::Text",
          "underlined": false,
          "variables": [],
          "effects": [],
          "behaviors": [],
          "string": "Score 0 ",
          "font": "",
          "characterSize": 20,
          "color": {
            "b": 0,
            "g": 0,
            "r": 0
          }
        },
        {
          "assetStoreId": "",
          "bold": false,
          "italic": false,
          "name": "debugger",
          "smoothed": true,
          "tags": "",
          "type": "TextObject::Text",
          "underlined": false,
          "variables": [],
          "effects": [],
          "behaviors": [],
          "string": "VAlor de Stop",
          "font": "",
          "characterSize": 20,
          "color": {
            "b": 0,
            "g": 0,
            "r": 0
          }
        }
      ],
      "events": [
        {
          "type": "BuiltinCommonInstructions::Standard",
          "conditions": [
            {
              "type": {
                "value": "DepartScene"
              },
              "parameters": [
                ""
              ]
            }
          ],
          "actions": [
            {
              "type": {
                "value": "MettreX"
              },
              "parameters": [
                "Ball",
                "=",
                "Rocky.X()"
              ]
            },
            {
              "type": {
                "value": "MettreY"
              },
              "parameters": [
                "Ball",
                "=",
                "Rocky.Y()  - Rocky.Height()"
              ]
            },
            {
              "type": {
                "value": "Cache"
              },
              "parameters": [
                "SolidUp"
              ]
            },
            {
              "type": {
                "value": "Cache"
              },
              "parameters": [
                "SolidDown"
              ]
            },
            {
              "type": {
                "value": "Cache"
              },
              "parameters": [
                "SolidoD"
              ]
            },
            {
              "type": {
                "value": "Cache"
              },
              "parameters": [
                "SolidoI"
              ]
            },
            {
              "type": {
                "value": "ResetTimer"
              },
              "parameters": [
                "",
                "\"CrearDinos\""
              ]
            }
          ]
        },
        {
          "type": "BuiltinCommonInstructions::Comment",
          "color": {
            "b": 109,
            "g": 230,
            "r": 255,
            "textB": 0,
            "textG": 0,
            "textR": 0
          },
          "comment": "Debug",
          "comment2": ""
        },
        {
          "type": "BuiltinCommonInstructions::Standard",
          "conditions": [
            {
              "type": {
                "value": "Toujours"
              },
              "parameters": [
                ""
              ]
            }
          ],
          "actions": [
            {
              "type": {
                "value": "DebuggerTools::ConsoleLog"
              },
              "parameters": [
                "\"El valor de Stop es \" + Ball.VariableString(State)",
                "\"info\"",
                "\"\""
              ]
            },
            {
              "type": {
                "value": "DebuggerTools::ConsoleLog"
              },
              "parameters": [
                "\"El valor de Time es \" + ToString(TimerElapsedTime(\"TimeBall\"))",
                "\"info\"",
                "\"\""
              ]
            },
            {
              "type": {
                "value": "TextObject::String"
              },
              "parameters": [
                "debugger",
                "=",
                "\"Valor state de Ball: \" +Ball.VariableString(State)"
              ]
            }
          ]
        },
        {
          "colorB": 228,
          "colorG": 176,
          "colorR": 74,
          "creationTime": 0,
          "name": "Player",
          "source": "",
          "type": "BuiltinCommonInstructions::Group",
          "events": [
            {
              "type": "BuiltinCommonInstructions::Standard",
              "conditions": [
                {
                  "type": {
                    "value": "CollisionNP"
                  },
                  "parameters": [
                    "Rocky",
                    "SolidoI",
                    "",
                    "",
                    ""
                  ]
                }
              ],
              "actions": [
                {
                  "type": {
                    "value": "MettreX"
                  },
                  "parameters": [
                    "Rocky",
                    "=",
                    "SolidoI.Width() + 66"
                  ]
                }
              ]
            },
            {
              "type": "BuiltinCommonInstructions::Standard",
              "conditions": [
                {
                  "type": {
                    "value": "CollisionNP"
                  },
                  "parameters": [
                    "Rocky",
                    "SolidoD",
                    "",
                    "",
                    ""
                  ]
                }
              ],
              "actions": [
                {
                  "type": {
                    "value": "MettreX"
                  },
                  "parameters": [
                    "Rocky",
                    "=",
                    "SceneWindowWidth() - Rocky.Width() - 73"
                  ]
                }
              ]
            },
            {
              "type": "BuiltinCommonInstructions::Standard",
              "conditions": [
                {
                  "type": {
                    "value": "KeyPressed"
                  },
                  "parameters": [
                    "",
                    "Space"
                  ]
                },
                {
                  "type": {
                    "value": "VarObjetTxt"
                  },
                  "parameters": [
                    "Ball",
                    "State",
                    "=",
                    "\"stop\""
                  ]
                }
              ],
              "actions": [
                {
                  "type": {
                    "value": "ModVarObjetTxt"
                  },
                  "parameters": [
                    "Ball",
                    "State",
                    "=",
                    "\"move\""
                  ]
                }
              ]
            },
            {
              "type": "BuiltinCommonInstructions::Standard",
              "conditions": [
                {
                  "type": {
                    "value": "KeyPressed"
                  },
                  "parameters": [
                    "Rocky",
                    "Left"
                  ]
                }
              ],
              "actions": [
                {
                  "type": {
                    "value": "AddForceXY"
                  },
                  "parameters": [
                    "Rocky",
                    "-300",
                    "0",
                    ""
                  ]
                }
              ]
            },
            {
              "type": "BuiltinCommonInstructions::Standard",
              "conditions": [
                {
                  "type": {
                    "value": "KeyPressed"
                  },
                  "parameters": [
                    "Rocky",
                    "Right"
                  ]
                }
              ],
              "actions": [
                {
                  "type": {
                    "value": "AddForceXY"
                  },
                  "parameters": [
                    "Rocky",
                    "300",
                    "0",
                    ""
                  ]
                }
              ]
            }
          ],
          "parameters": []
        },
        {
          "colorB": 228,
          "colorG": 176,
          "colorR": 74,
          "creationTime": 0,
          "name": "Ball",
          "source": "",
          "type": "BuiltinCommonInstructions::Group",
          "events": [
            {
              "type": "BuiltinCommonInstructions::Standard",
              "conditions": [
                {
                  "type": {
                    "value": "PosY"
                  },
                  "parameters": [
                    "Ball",
                    ">",
                    "SceneWindowHeight() + 50"
                  ]
                }
              ],
              "actions": [
                {
                  "type": {
                    "value": "ModVarObjetTxt"
                  },
                  "parameters": [
                    "Ball",
                    "State",
                    "=",
                    "\"out\""
                  ]
                },
                {
                  "type": {
                    "value": "TextObject::String"
                  },
                  "parameters": [
                    "Score",
                    "=",
                    "\"Score \" + GlobalVariableString(Score)"
                  ]
                }
              ],
              "events": [
                {
                  "type": "BuiltinCommonInstructions::Standard",
                  "conditions": [
                    {
                      "type": {
                        "value": "BuiltinCommonInstructions::Once"
                      },
                      "parameters": []
                    }
                  ],
                  "actions": [
                    {
                      "type": {
                        "value": "ModVarGlobal"
                      },
                      "parameters": [
                        "Score",
                        "-",
                        "1"
                      ]
                    }
                  ]
                }
              ]
            },
            {
              "type": "BuiltinCommonInstructions::Standard",
              "conditions": [
                {
                  "type": {
                    "value": "CompareTimer"
                  },
                  "parameters": [
                    "",
                    "\"TimeBall\"",
                    ">=",
                    "1"
                  ]
                }
              ],
              "actions": [
                {
                  "type": {
                    "value": "ModVarObjetTxt"
                  },
                  "parameters": [
                    "Ball",
                    "State",
                    "=",
                    "\"stop\""
                  ]
                },
                {
                  "type": {
                    "value": "RemoveTimer"
                  },
                  "parameters": [
                    "",
                    "\"TimeBall\""
                  ]
                }
              ]
            },
            {
              "type": "BuiltinCommonInstructions::Standard",
              "conditions": [
                {
                  "type": {
                    "value": "VarObjetTxt"
                  },
                  "parameters": [
                    "Ball",
                    "State",
                    "=",
                    "\"move\""
                  ]
                }
              ],
              "actions": [
                {
                  "type": {
                    "value": "MettreX"
                  },
                  "parameters": [
                    "Ball",
                    "+",
                    "Ball.Variable(DirX)"
                  ]
                },
                {
                  "type": {
                    "value": "MettreY"
                  },
                  "parameters": [
                    "Ball",
                    "+",
                    "Ball.Variable(DirY)"
                  ]
                },
                {
                  "type": {
                    "value": "Rotate"
                  },
                  "parameters": [
                    "Ball",
                    "Ball.Variable(Speed)",
                    ""
                  ]
                }
              ]
            },
            {
              "type": "BuiltinCommonInstructions::Standard",
              "conditions": [
                {
                  "type": {
                    "value": "VarObjetTxt"
                  },
                  "parameters": [
                    "Ball",
                    "State",
                    "=",
                    "\"stop\""
                  ]
                }
              ],
              "actions": [
                {
                  "type": {
                    "value": "MettreX"
                  },
                  "parameters": [
                    "Ball",
                    "=",
                    "Rocky.X()"
                  ]
                },
                {
                  "type": {
                    "value": "MettreY"
                  },
                  "parameters": [
                    "Ball",
                    "=",
                    "Rocky.Y()  - Rocky.Height()"
                  ]
                },
                {
                  "type": {
                    "value": "ModVarObjet"
                  },
                  "parameters": [
                    "Ball",
                    "DirY",
                    "=",
                    "-5"
                  ]
                }
              ]
            },
            {
              "type": "BuiltinCommonInstructions::Standard",
              "conditions": [
                {
                  "type": {
                    "value": "VarObjetTxt"
                  },
                  "parameters": [
                    "Ball",
                    "State",
                    "=",
                    "\"out\""
                  ]
                }
              ],
              "actions": [
                {
                  "type": {
                    "value": "MettreX"
                  },
                  "parameters": [
                    "Ball",
                    "=",
                    "\nSceneWindowWidth() + 100"
                  ]
                },
                {
                  "type": {
                    "value": "MettreY"
                  },
                  "parameters": [
                    "Ball",
                    "=",
                    "\nSceneWindowHeight() + 100"
                  ]
                }
              ],
              "events": [
                {
                  "type": "BuiltinCommonInstructions::Standard",
                  "conditions": [
                    {
                      "type": {
                        "value": "BuiltinCommonInstructions::Once"
                      },
                      "parameters": []
                    }
                  ],
                  "actions": [
                    {
                      "type": {
                        "value": "ResetTimer"
                      },
                      "parameters": [
                        "",
                        "\"TimeBall\""
                      ]
                    }
                  ]
                }
              ]
            },
            {
              "type": "BuiltinCommonInstructions::Standard",
              "conditions": [
                {
                  "type": {
                    "value": "CollisionNP"
                  },
                  "parameters": [
                    "Ball",
                    "SolidUp",
                    "",
                    "",
                    ""
                  ]
                }
              ],
              "actions": [
                {
                  "type": {
                    "value": "ModVarObjet"
                  },
                  "parameters": [
                    "Ball",
                    "DirY",
                    "=",
                    "5"
                  ]
                }
              ]
            },
            {
              "type": "BuiltinCommonInstructions::Standard",
              "conditions": [
                {
                  "type": {
                    "value": "CollisionNP"
                  },
                  "parameters": [
                    "Ball",
                    "SolidoI",
                    "",
                    "",
                    ""
                  ]
                }
              ],
              "actions": [
                {
                  "type": {
                    "value": "ModVarObjet"
                  },
                  "parameters": [
                    "Ball",
                    "DirX",
                    "=",
                    "5"
                  ]
                }
              ]
            },
            {
              "type": "BuiltinCommonInstructions::Standard",
              "conditions": [
                {
                  "type": {
                    "value": "CollisionNP"
                  },
                  "parameters": [
                    "Ball",
                    "SolidoD",
                    "",
                    "",
                    ""
                  ]
                }
              ],
              "actions": [
                {
                  "type": {
                    "value": "ModVarObjet"
                  },
                  "parameters": [
                    "Ball",
                    "DirX",
                    "=",
                    "-5"
                  ]
                }
              ]
            },
            {
              "type": "BuiltinCommonInstructions::Standard",
              "conditions": [
                {
                  "type": {
                    "value": "CollisionNP"
                  },
                  "parameters": [
                    "Ball",
                    "Rocky",
                    "",
                    "",
                    ""
                  ]
                },
                {
                  "type": {
                    "value": "VarObjetTxt"
                  },
                  "parameters": [
                    "Ball",
                    "State",
                    "=",
                    "\"move\""
                  ]
                }
              ],
              "actions": [
                {
                  "type": {
                    "value": "ModVarObjetTxt"
                  },
                  "parameters": [
                    "Ball",
                    "State",
                    "=",
                    "\"stop\""
                  ]
                }
              ]
            }
          ],
          "parameters": []
        },
        {
          "type": "BuiltinCommonInstructions::Standard",
          "conditions": [],
          "actions": []
        },
        {
          "colorB": 228,
          "colorG": 176,
          "colorR": 74,
          "creationTime": 0,
          "name": "Dinos",
          "source": "",
          "type": "BuiltinCommonInstructions::Group",
          "events": [
            {
              "type": "BuiltinCommonInstructions::Standard",
              "conditions": [
                {
                  "type": {
                    "value": "CompareTimer"
                  },
                  "parameters": [
                    "",
                    "\"CrearDinos\"",
                    ">=",
                    "3"
                  ]
                }
              ],
              "actions": [
                {
                  "type": {
                    "value": "Create"
                  },
                  "parameters": [
                    "",
                    "Dino",
                    "RandomInRange(100, SceneWindowWidth() - 100)",
                    "-20",
                    ""
                  ]
                },
                {
                  "type": {
                    "value": "ResetTimer"
                  },
                  "parameters": [
                    "",
                    "\"CrearDinos\""
                  ]
                }
              ]
            },
            {
              "type": "BuiltinCommonInstructions::Standard",
              "conditions": [],
              "actions": [
                {
                  "type": {
                    "value": "AddForceXY"
                  },
                  "parameters": [
                    "Dino",
                    "0",
                    "150",
                    ""
                  ]
                }
              ]
            }
          ],
          "parameters": []
        }
      ],
      "layers": [
        {
          "ambientLightColorB": 0,
          "ambientLightColorG": 0,
          "ambientLightColorR": 0,
          "followBaseLayerCamera": false,
          "isLightingLayer": false,
          "name": "",
          "visibility": true,
          "cameras": [
            {
              "defaultSize": true,
              "defaultViewport": true,
              "height": 0,
              "viewportBottom": 1,
              "viewportLeft": 0,
              "viewportRight": 1,
              "viewportTop": 0,
              "width": 0
            }
          ],
          "effects": []
        }
      ],
      "behaviorsSharedData": [
        {
          "name": "Physics2",
          "type": "Physics2::Physics2Behavior",
          "gravityX": 0,
          "gravityY": 9.8,
          "scaleX": 100,
          "scaleY": 100
        }
      ]
    }
  ],
  "externalEvents": [],
  "eventsFunctionsExtensions": [
    {
      "author": "@4ian",
      "category": "",
      "description": "Force the object to stay visible on the screen by setting back its position inside the viewport of the camera.",
      "extensionNamespace": "",
      "fullName": "Stay On Screen",
      "helpPath": "",
      "iconUrl": "data:image/svg+xml;base64,PD94bWwgdmVyc2lvbj0iMS4wIiBlbmNvZGluZz0iVVRGLTgiPz48IURPQ1RZUEUgc3ZnIFBVQkxJQyAiLS8vVzNDLy9EVEQgU1ZHIDEuMS8vRU4iICJodHRwOi8vd3d3LnczLm9yZy9HcmFwaGljcy9TVkcvMS4xL0RURC9zdmcxMS5kdGQiPjxzdmcgeG1sbnM9Imh0dHA6Ly93d3cudzMub3JnLzIwMDAvc3ZnIiB4bWxuczp4bGluaz0iaHR0cDovL3d3dy53My5vcmcvMTk5OS94bGluayIgdmVyc2lvbj0iMS4xIiBpZD0ibWRpLW1vbml0b3Itc2NyZWVuc2hvdCIgd2lkdGg9IjI0IiBoZWlnaHQ9IjI0IiB2aWV3Qm94PSIwIDAgMjQgMjQiPjxwYXRoIGQ9Ik05LDZINVYxMEg3VjhIOU0xOSwxMEgxN1YxMkgxNVYxNEgxOU0yMSwxNkgzVjRIMjFNMjEsMkgzQzEuODksMiAxLDIuODkgMSw0VjE2QTIsMiAwIDAsMCAzLDE4SDEwVjIwSDhWMjJIMTZWMjBIMTRWMThIMjFBMiwyIDAgMCwwIDIzLDE2VjRDMjMsMi44OSAyMi4xLDIgMjEsMiIgLz48L3N2Zz4=",
      "name": "StayOnScreen",
      "previewIconUrl": "https://resources.gdevelop-app.com/assets/Icons/monitor-screenshot.svg",
      "shortDescription": "Force the object to stay visible on the screen by setting back its position inside the viewport of the camera.",
      "version": "0.0.2",
      "origin": {
        "identifier": "StayOnScreen",
        "name": "gdevelop-extension-store"
      },
      "tags": [
        "positioning",
        "camera",
        "screen"
      ],
      "authorIds": [
        "wWP8BSlAW0UP4NeaHa2LcmmDzmH2",
        "2OwwM8ToR9dx9RJ2sAKTcrLmCB92"
      ],
      "dependencies": [],
      "eventsFunctions": [],
      "eventsBasedBehaviors": [
        {
          "description": "Force the object to stay visible on the screen by setting back its position inside the viewport of the camera.",
          "fullName": "Stay on Screen",
          "name": "StayOnScreen",
          "objectType": "",
          "eventsFunctions": [
            {
              "description": "",
              "fullName": "",
              "functionType": "Action",
              "group": "",
              "name": "doStepPostEvents",
              "private": false,
              "sentence": "",
              "events": [
                {
                  "type": "BuiltinCommonInstructions::Standard",
                  "conditions": [],
                  "actions": [
                    {
                      "type": {
                        "value": "MettreX"
                      },
                      "parameters": [
                        "Object",
                        "=",
                        "min(max(Object.X(), CameraX(Object.Layer(), 0) - CameraWidth(Object.Layer(), 0)/2 + Object.Behavior::PropertyMarginLeft()), CameraX(Object.Layer(), 0) + CameraWidth(Object.Layer(), 0)/2 - Object.Width() - Object.Behavior::PropertyMarginRight())"
                      ]
                    },
                    {
                      "type": {
                        "value": "MettreY"
                      },
                      "parameters": [
                        "Object",
                        "=",
                        "min(max(Object.Y(), CameraY(Object.Layer(), 0) - CameraHeight(Object.Layer(), 0)/2+ Object.Behavior::PropertyMarginTop()), CameraY(Object.Layer(), 0) + CameraHeight(Object.Layer(), 0)/2 - Object.Height() - Object.Behavior::PropertyMarginBottom())"
                      ]
                    }
                  ]
                }
              ],
              "parameters": [
                {
                  "codeOnly": false,
                  "defaultValue": "",
                  "description": "Object",
                  "longDescription": "",
                  "name": "Object",
                  "optional": false,
                  "supplementaryInformation": "",
                  "type": "object"
                },
                {
                  "codeOnly": false,
                  "defaultValue": "",
                  "description": "Behavior",
                  "longDescription": "",
                  "name": "Behavior",
                  "optional": false,
                  "supplementaryInformation": "StayOnScreen::StayOnScreen",
                  "type": "behavior"
                }
              ],
              "objectGroups": []
            }
          ],
          "propertyDescriptors": [
            {
              "value": "0",
              "type": "Number",
              "label": "Top margin, in pixels",
              "description": "",
              "group": "",
              "extraInformation": [],
              "hidden": false,
              "name": "MarginTop"
            },
            {
              "value": "0",
              "type": "Number",
              "label": "Bottom margin, in pixels",
              "description": "",
              "group": "",
              "extraInformation": [],
              "hidden": false,
              "name": "MarginBottom"
            },
            {
              "value": "0",
              "type": "Number",
              "label": "Left margin, in pixels",
              "description": "",
              "group": "",
              "extraInformation": [],
              "hidden": false,
              "name": "MarginLeft"
            },
            {
              "value": "0",
              "type": "Number",
              "label": "Right margin, in pixels",
              "description": "",
              "group": "",
              "extraInformation": [],
              "hidden": false,
              "name": "MarginRight"
            }
          ]
        }
      ]
    }
  ],
  "externalLayouts": [],
  "externalSourceFiles": []
}